docugami/__init__.py
docugami/_base_client.py
docugami/_client.py
docugami/_compat.py
docugami/_constants.py
docugami/_exceptions.py
docugami/_files.py
docugami/_models.py
docugami/_qs.py
docugami/_resource.py
docugami/_response.py
docugami/_streaming.py
docugami/_types.py
docugami/_version.py
docugami/pagination.py
docugami/py.typed
docugami/_utils/__init__.py
docugami/_utils/_logs.py
docugami/_utils/_proxy.py
docugami/_utils/_transform.py
docugami/_utils/_utils.py
docugami/lib/upload.py
docugami/resources/__init__.py
docugami/resources/webhooks.py
docugami/resources/workspaces.py
docugami/resources/docsets/__init__.py
docugami/resources/docsets/docsets.py
docugami/resources/docsets/documents.py
docugami/resources/documents/__init__.py
docugami/resources/documents/contents.py
docugami/resources/documents/documents.py
docugami/resources/projects/__init__.py
docugami/resources/projects/projects.py
docugami/resources/projects/artifacts/__init__.py
docugami/resources/projects/artifacts/artifacts.py
docugami/resources/projects/artifacts/contents.py
docugami/types/__init__.py
docugami/types/docset.py
docugami/types/docset_create_params.py
docugami/types/docset_list_params.py
docugami/types/document.py
docugami/types/document_list_params.py
docugami/types/project.py
docugami/types/project_list_params.py
docugami/types/webhook.py
docugami/types/webhook_create_params.py
docugami/types/webhook_list_params.py
docugami/types/workspace.py
docugami/types/docsets/__init__.py
docugami/types/docsets/document_dgml_response.py
docugami/types/docsets/document_list_params.py
docugami/types/documents/__init__.py
docugami/types/documents/content_upload_params.py
docugami/types/projects/__init__.py
docugami/types/projects/artifact.py
docugami/types/projects/artifact_list_params.py
docugami/types/projects/artifacts/__init__.py
docugami/types/projects/artifacts/content_upload_params.py
docugami-0.1.2.dist-info/METADATA
docugami-0.1.2.dist-info/WHEEL
docugami-0.1.2.dist-info/licenses/LICENSE
docugami-0.1.2.dist-info/RECORD
