Metadata-Version: 2.1
Name: docugami
Version: 0.1.2
Summary: The official Python library for the Docugami API
Project-URL: Homepage, https://github.com/docugami/docugami-python
Project-URL: Repository, https://github.com/docugami/docugami-python
Author-email: Docugami <contact@docugami.com>
License-Expression: MIT
License-File: LICENSE
Classifier: Intended Audience :: Developers
Classifier: License :: OSI Approved :: MIT License
Classifier: Operating System :: MacOS
Classifier: Operating System :: Microsoft :: Windows
Classifier: Operating System :: OS Independent
Classifier: Operating System :: POSIX
Classifier: Operating System :: POSIX :: Linux
Classifier: Programming Language :: Python :: 3.7
Classifier: Programming Language :: Python :: 3.8
Classifier: Programming Language :: Python :: 3.9
Classifier: Programming Language :: Python :: 3.10
Classifier: Programming Language :: Python :: 3.11
Classifier: Programming Language :: Python :: 3.12
Classifier: Topic :: Software Development :: Libraries :: Python Modules
Classifier: Typing :: Typed
Requires-Python: >=3.7
Requires-Dist: anyio<5,>=3.5.0
Requires-Dist: distro<2,>=1.7.0
Requires-Dist: httpx<1,>=0.23.0
Requires-Dist: pydantic<3,>=1.9.0
Requires-Dist: requests>=2.31.0
Requires-Dist: sniffio
Requires-Dist: types-requests>=2.31.0.10
Requires-Dist: typing-extensions<5,>=4.5
